Metadata-Version: 1.1
Name: django-live-support
Version: 0.1.9
Summary: A django app that lets you chat with visitors to your site.
Home-page: http://github.com/megamark16/django-live-support
Author: Mark Ransom
Author-email: megamark16@gmail.com
License: BSD
Platform: OS Independent
Classifier: Development Status :: 4 - Beta
Classifier: Framework :: Django
Classifier: Intended Audience :: Developers
Classifier: License :: OSI Approved :: BSD License
Classifier: Operating System :: OS Independent
Classifier: Programming Language :: Python
Classifier: Topic :: Internet :: WWW/HTTP
Classifier: Topic :: Communications :: Chat
